riskhub/__init__.py
riskhub/riskhub.py
riskhub-0.2.dist-info/METADATA
riskhub-0.2.dist-info/WHEEL
riskhub-0.2.dist-info/entry_points.txt
riskhub-0.2.dist-info/top_level.txt
riskhub-0.2.dist-info/RECORD
