Metadata-Version: 2.1
Name: riskhub
Version: 0.2
Summary: fetching URLs to any domains
Home-page: UNKNOWN
Author: sabarish
Author-email: sabarishbugbounty@gmail.com
License: UNKNOWN
Platform: UNKNOWN
Requires-Dist: requests (==2.27.1)
Requires-Dist: argparse (==1.4.0)
Requires-Dist: apscheduler (==3.9.1)
Requires-Dist: urllib3 (==1.24.2)
Requires-Dist: APScheduler (==3.9.1)
Requires-Dist: httplib2 (==0.22.0)
